[
    {"identificador":1, 
    "nombre":"Argo", 
    "descripcion":"",
    "modelo": "2022",
    "color": "negro",
    "imagen":"https://http2.mlstatic.com/D_NQ_NP_2X_742192-MLA50463631044_062022-F.webp", 
    "precio":2200000, 
    "stock":5, 
    "categoria":"Fiat"},

    {"identificador":2, 
    "nombre":"Ranger", 
    "descripcion":"",
    "modelo": "2022",
    "color": "gris",
    "imagen":"https://http2.mlstatic.com/D_NQ_NP_2X_894505-MLA25028831902_082016-F.webp", 
    "precio":3200000, 
    "stock":10, 
    "categoria":"Ford"},

    {"identificador":3, 
    "nombre":"C3", 
    "descripcion":"",
    "modelo": "2003",
    "color": "blanco",
    "imagen":"https://http2.mlstatic.com/D_NQ_NP_2X_765243-MLA51850784193_102022-F.webp", 
    "precio":1500000, 
    "stock":1, 
    "categoria":"Citroen"},
    
    {"identificador":4, 
    "nombre":"Serie 1", 
    "descripcion":"", 
    "modelo": "2018",
    "color": "azul",
    "imagen":"https://http2.mlstatic.com/D_NQ_NP_2X_830749-MLA52043855118_102022-F.webp", 
    "precio":5200000, 
    "stock":1, 
    "categoria":"Bmw"},
    
    {"identificador":5, 
    "nombre":"Mustang", 
    "descripcion":"", 
    "imagen":"https://http2.mlstatic.com/D_NQ_NP_2X_993903-MLA51954941462_102022-F.webp", 
    "precio":8200000, 
    "stock":1, 
    "categoria":"Ford"},
    
    {"identificador":6, 
    "nombre":"Cruze", 
    "descripcion":"", 
    "modelo": "2005",
    "color": "Negro",
    "imagen":"https://http2.mlstatic.com/D_NQ_NP_2X_921642-MLA45975661166_052021-F.webp", 
    "precio":2000000, 
    "stock":2, 
    "categoria":"Chevrolet"},

    {"identificador":7, 
    "nombre":"Cronos",
    "descripcion":"",
    "modelo": "2023",
    "color": "gris",
    "imagen":"https://http2.mlstatic.com/D_NQ_NP_2X_833933-MLA52086645353_102022-F.webp", 
    "precio":3000000, 
    "stock":8, 
    "categoria":"Fiat"},

    {"identificador":8, 
    "nombre":"Corola", 
    "descripcion":"", 
    "imagen":"https://http2.mlstatic.com/D_NQ_NP_2X_774302-MLA51676616807_092022-F.webp", 
    "precio":3820000, 
    "modelo": "2022",
    "color": "Blanco",
    "stock":4, 
    "categoria":"Toyota"},

    {"identificador":9, 
    "nombre":"Sentra", 
    "descripcion":"", 
    "modelo": "2022",
    "color": "negro",
    "imagen":"https://http2.mlstatic.com/D_NQ_NP_2X_649038-MLA51469429826_092022-F.webp", 
    "precio":3900000, 
    "stock":9, 
    "categoria":"Nissan"}
]